acme/__init__.py
acme/__main__.py
acme/bleach/__init__.py
acme/bleach/app.py
acme/bleach/codec.py
acme/py.typed
acme_bleach-0.2.3.dist-info/entry_points.txt
acme_bleach-0.2.3.dist-info/WHEEL
acme_bleach-0.2.3.dist-info/LICENSE
acme_bleach-0.2.3.dist-info/METADATA
acme_bleach-0.2.3.dist-info/RECORD
