Metadata-Version: 2.1
Name: acme-bleach
Version: 0.2.3
Summary: Remove unsightly non-whitespace characters from your code.
Home-page: https://github.com/stefansm/acme-bleach
License: MIT
Author: Stefans Mezulis
Author-email: stefans.mezulis@gmail.com
Requires-Python: >=3.10,<4.0
Classifier: Development Status :: 1 - Planning
Classifier: License :: OSI Approved :: MIT License
Classifier: Programming Language :: Python :: 3
Classifier: Programming Language :: Python :: 3.10
Classifier: Programming Language :: Python :: 3.11
Requires-Dist: click (>=8.1,<9.0)
Project-URL: Changelog, https://github.com/stefansm/acme-bleach/releases
Project-URL: Documentation, https://acme-bleach.readthedocs.io
Project-URL: Repository, https://github.com/stefansm/acme-bleach
